Metadata-Version: 1.0
Name: simple-probability-distributions
Version: 0.1
Summary: Gaussian and Binomial distributions
Home-page: UNKNOWN
Author: Bello Ramon
Author-email: belloramon2014@gmail.com
License: UNKNOWN
Platform: UNKNOWN
